{"nodes": [{"id": "c_users_cristian_documents_progetti_jarvis_frameworkutenti_seed_seed_core_daemon_py", "label": "daemon.py", "file_type": "code", "source_file": "seed/core/daemon.py", "source_location": "L1"}, {"id": "core_daemon_daemonerror", "label": "DaemonError", "file_type": "code", "source_file": "seed/core/daemon.py", "source_location": "L71"}, {"id": "valueerror", "label": "ValueError", "file_type": "code", "source_file": "", "source_location": ""}, {"id": "core_daemon_clamp_cost", "label": "_clamp_cost()", "file_type": "code", "source_file": "seed/core/daemon.py", "source_location": "L75"}, {"id": "core_daemon_proactivitycandidate", "label": "ProactivityCandidate", "file_type": "code", "source_file": "seed/core/daemon.py", "source_location": "L83"}, {"id": "core_daemon_proactivitycandidate_validate", "label": ".validate()", "file_type": "code", "source_file": "seed/core/daemon.py", "source_location": "L97"}, {"id": "core_daemon_proactivitydecision", "label": "ProactivityDecision", "file_type": "code", "source_file": "seed/core/daemon.py", "source_location": "L110"}, {"id": "core_daemon_governed_net_value", "label": "governed_net_value()", "file_type": "code", "source_file": "seed/core/daemon.py", "source_location": "L118"}, {"id": "core_daemon_decide_proactivity", "label": "decide_proactivity()", "file_type": "code", "source_file": "seed/core/daemon.py", "source_location": "L129"}, {"id": "core_daemon_heartbeatstats", "label": "HeartbeatStats", "file_type": "code", "source_file": "seed/core/daemon.py", "source_location": "L178"}, {"id": "core_daemon_heartbeatstats_record", "label": ".record()", "file_type": "code", "source_file": "seed/core/daemon.py", "source_location": "L185"}, {"id": "core_daemon_build_heartbeat", "label": "build_heartbeat()", "file_type": "code", "source_file": "seed/core/daemon.py", "source_location": "L191"}, {"id": "core_daemon_backgrounddaemon", "label": "BackgroundDaemon", "file_type": "code", "source_file": "seed/core/daemon.py", "source_location": "L219"}, {"id": "core_daemon_backgrounddaemon_init", "label": ".__init__()", "file_type": "code", "source_file": "seed/core/daemon.py", "source_location": "L226"}, {"id": "core_daemon_backgrounddaemon_start", "label": ".start()", "file_type": "code", "source_file": "seed/core/daemon.py", "source_location": "L252"}, {"id": "core_daemon_backgrounddaemon_stop", "label": ".stop()", "file_type": "code", "source_file": "seed/core/daemon.py", "source_location": "L267"}, {"id": "core_daemon_backgrounddaemon_running", "label": ".running()", "file_type": "code", "source_file": "seed/core/daemon.py", "source_location": "L275"}, {"id": "core_daemon_backgrounddaemon_enqueue", "label": ".enqueue()", "file_type": "code", "source_file": "seed/core/daemon.py", "source_location": "L279"}, {"id": "core_daemon_backgrounddaemon_suppress_category", "label": ".suppress_category()", "file_type": "code", "source_file": "seed/core/daemon.py", "source_location": "L296"}, {"id": "core_daemon_backgrounddaemon_review", "label": ".review()", "file_type": "code", "source_file": "seed/core/daemon.py", "source_location": "L305"}, {"id": "core_daemon_backgrounddaemon_loop", "label": "._loop()", "file_type": "code", "source_file": "seed/core/daemon.py", "source_location": "L331"}, {"id": "core_daemon_backgrounddaemon_tick", "label": "._tick()", "file_type": "code", "source_file": "seed/core/daemon.py", "source_location": "L337"}, {"id": "core_daemon_backgrounddaemon_tick_locked", "label": "._tick_locked()", "file_type": "code", "source_file": "seed/core/daemon.py", "source_location": "L344"}, {"id": "core_daemon_backgrounddaemon_apply_decision", "label": "._apply_decision()", "file_type": "code", "source_file": "seed/core/daemon.py", "source_location": "L378"}, {"id": "core_daemon_backgrounddaemon_row_to_candidate", "label": "._row_to_candidate()", "file_type": "code", "source_file": "seed/core/daemon.py", "source_location": "L395"}, {"id": "core_daemon_new_candidate_id", "label": "new_candidate_id()", "file_type": "code", "source_file": "seed/core/daemon.py", "source_location": "L409"}, {"id": "core_daemon_rationale_1", "label": "D1: daemon agentico in background, SOLO a PC acceso e dentro SEED.  Il daemon vi", "file_type": "rationale", "source_file": "seed/core/daemon.py", "source_location": "L1"}, {"id": "core_daemon_rationale_72", "label": "Sollevata quando una candidate violerebbe i confini D1.", "file_type": "rationale", "source_file": "seed/core/daemon.py", "source_location": "L72"}, {"id": "core_daemon_rationale_84", "label": "Una proposta di proattivita'. NON contiene testo personale: solo una     categor", "file_type": "rationale", "source_file": "seed/core/daemon.py", "source_location": "L84"}, {"id": "core_daemon_rationale_119", "label": "Formula harness (doc 16): parla solo se il valore atteso supera la somma     dei", "file_type": "rationale", "source_file": "seed/core/daemon.py", "source_location": "L119"}, {"id": "core_daemon_rationale_138", "label": "Decisione deterministica e spiegabile. Default = silenzio.      Ordine dei gate:", "file_type": "rationale", "source_file": "seed/core/daemon.py", "source_location": "L138"}, {"id": "core_daemon_rationale_193", "label": "Battito aggregato e rivedibile. Dichiara esplicitamente i confini D1 e     non c", "file_type": "rationale", "source_file": "seed/core/daemon.py", "source_location": "L193"}, {"id": "core_daemon_rationale_220", "label": "Loop di background supervisionato, in-process. Mirroring di `Scheduler`:     thr", "file_type": "rationale", "source_file": "seed/core/daemon.py", "source_location": "L220"}, {"id": "core_daemon_rationale_280", "label": "Accoda una candidate gia' validata (categoria ammessa, ref opaco).         Rifiu", "file_type": "rationale", "source_file": "seed/core/daemon.py", "source_location": "L280"}, {"id": "core_daemon_rationale_306", "label": "Snapshot aggregato e rivedibile: stato daemon, conteggi coda e flag         che", "file_type": "rationale", "source_file": "seed/core/daemon.py", "source_location": "L306"}], "edges": [{"source": "c_users_cristian_documents_progetti_jarvis_frameworkutenti_seed_seed_core_daemon_py", "target": "logging", "relation": "imports", "context": "import", "confidence": "EXTRACTED", "source_file": "seed/core/daemon.py", "source_location": "L26", "weight": 1.0}, {"source": "c_users_cristian_documents_progetti_jarvis_frameworkutenti_seed_seed_core_daemon_py", "target": "re", "relation": "imports", "context": "import", "confidence": "EXTRACTED", "source_file": "seed/core/daemon.py", "source_location": "L27", "weight": 1.0}, {"source": "c_users_cristian_documents_progetti_jarvis_frameworkutenti_seed_seed_core_daemon_py", "target": "threading", "relation": "imports", "context": "import", "confidence": "EXTRACTED", "source_file": "seed/core/daemon.py", "source_location": "L28", "weight": 1.0}, {"source": "c_users_cristian_documents_progetti_jarvis_frameworkutenti_seed_seed_core_daemon_py", "target": "time", "relation": "imports", "context": "import", "confidence": "EXTRACTED", "source_file": "seed/core/daemon.py", "source_location": "L29", "weight": 1.0}, {"source": "c_users_cristian_documents_progetti_jarvis_frameworkutenti_seed_seed_core_daemon_py", "target": "uuid", "relation": "imports", "context": "import", "confidence": "EXTRACTED", "source_file": "seed/core/daemon.py", "source_location": "L30", "weight": 1.0}, {"source": "c_users_cristian_documents_progetti_jarvis_frameworkutenti_seed_seed_core_daemon_py", "target": "dataclasses", "relation": "imports_from", "context": "import", "confidence": "EXTRACTED", "source_file": "seed/core/daemon.py", "source_location": "L31", "weight": 1.0}, {"source": "c_users_cristian_documents_progetti_jarvis_frameworkutenti_seed_seed_core_daemon_py", "target": "core_daemon_daemonerror", "relation": "contains", "confidence": "EXTRACTED", "source_file": "seed/core/daemon.py", "source_location": "L71", "weight": 1.0}, {"source": "core_daemon_daemonerror", "target": "valueerror", "relation": "inherits", "confidence": "EXTRACTED", "source_file": "seed/core/daemon.py", "source_location": "L71", "weight": 1.0}, {"source": "c_users_cristian_documents_progetti_jarvis_frameworkutenti_seed_seed_core_daemon_py", "target": "core_daemon_clamp_cost", "relation": "contains", "confidence": "EXTRACTED", "source_file": "seed/core/daemon.py", "source_location": "L75", "weight": 1.0}, {"source": "c_users_cristian_documents_progetti_jarvis_frameworkutenti_seed_seed_core_daemon_py", "target": "core_daemon_proactivitycandidate", "relation": "contains", "confidence": "EXTRACTED", "source_file": "seed/core/daemon.py", "source_location": "L83", "weight": 1.0}, {"source": "core_daemon_proactivitycandidate", "target": "core_daemon_proactivitycandidate_validate", "relation": "method", "confidence": "EXTRACTED", "source_file": "seed/core/daemon.py", "source_location": "L97", "weight": 1.0}, {"source": "c_users_cristian_documents_progetti_jarvis_frameworkutenti_seed_seed_core_daemon_py", "target": "core_daemon_proactivitydecision", "relation": "contains", "confidence": "EXTRACTED", "source_file": "seed/core/daemon.py", "source_location": "L110", "weight": 1.0}, {"source": "c_users_cristian_documents_progetti_jarvis_frameworkutenti_seed_seed_core_daemon_py", "target": "core_daemon_governed_net_value", "relation": "contains", "confidence": "EXTRACTED", "source_file": "seed/core/daemon.py", "source_location": "L118", "weight": 1.0}, {"source": "core_daemon_governed_net_value", "target": "core_daemon_proactivitycandidate", "relation": "references", "context": "parameter_type", "confidence": "EXTRACTED", "source_file": "seed/core/daemon.py", "source_location": "L118", "weight": 1.0}, {"source": "c_users_cristian_documents_progetti_jarvis_frameworkutenti_seed_seed_core_daemon_py", "target": "core_daemon_decide_proactivity", "relation": "contains", "confidence": "EXTRACTED", "source_file": "seed/core/daemon.py", "source_location": "L129", "weight": 1.0}, {"source": "core_daemon_decide_proactivity", "target": "core_daemon_proactivitycandidate", "relation": "references", "context": "parameter_type", "confidence": "EXTRACTED", "source_file": "seed/core/daemon.py", "source_location": "L129", "weight": 1.0}, {"source": "core_daemon_decide_proactivity", "target": "core_daemon_proactivitydecision", "relation": "references", "context": "return_type", "confidence": "EXTRACTED", "source_file": "seed/core/daemon.py", "source_location": "L129", "weight": 1.0}, {"source": "c_users_cristian_documents_progetti_jarvis_frameworkutenti_seed_seed_core_daemon_py", "target": "core_daemon_heartbeatstats", "relation": "contains", "confidence": "EXTRACTED", "source_file": "seed/core/daemon.py", "source_location": "L178", "weight": 1.0}, {"source": "core_daemon_heartbeatstats", "target": "core_daemon_heartbeatstats_record", "relation": "method", "confidence": "EXTRACTED", "source_file": "seed/core/daemon.py", "source_location": "L185", "weight": 1.0}, {"source": "c_users_cristian_documents_progetti_jarvis_frameworkutenti_seed_seed_core_daemon_py", "target": "core_daemon_build_heartbeat", "relation": "contains", "confidence": "EXTRACTED", "source_file": "seed/core/daemon.py", "source_location": "L191", "weight": 1.0}, {"source": "core_daemon_build_heartbeat", "target": "core_daemon_heartbeatstats", "relation": "references", "context": "parameter_type", "confidence": "EXTRACTED", "source_file": "seed/core/daemon.py", "source_location": "L191", "weight": 1.0}, {"source": "c_users_cristian_documents_progetti_jarvis_frameworkutenti_seed_seed_core_daemon_py", "target": "core_daemon_backgrounddaemon", "relation": "contains", "confidence": "EXTRACTED", "source_file": "seed/core/daemon.py", "source_location": "L219", "weight": 1.0}, {"source": "core_daemon_backgrounddaemon", "target": "core_daemon_backgrounddaemon_init", "relation": "method", "confidence": "EXTRACTED", "source_file": "seed/core/daemon.py", "source_location": "L226", "weight": 1.0}, {"source": "core_daemon_backgrounddaemon", "target": "core_daemon_backgrounddaemon_start", "relation": "method", "confidence": "EXTRACTED", "source_file": "seed/core/daemon.py", "source_location": "L252", "weight": 1.0}, {"source": "core_daemon_backgrounddaemon", "target": "core_daemon_backgrounddaemon_stop", "relation": "method", "confidence": "EXTRACTED", "source_file": "seed/core/daemon.py", "source_location": "L267", "weight": 1.0}, {"source": "core_daemon_backgrounddaemon", "target": "core_daemon_backgrounddaemon_running", "relation": "method", "confidence": "EXTRACTED", "source_file": "seed/core/daemon.py", "source_location": "L275", "weight": 1.0}, {"source": "core_daemon_backgrounddaemon", "target": "core_daemon_backgrounddaemon_enqueue", "relation": "method", "confidence": "EXTRACTED", "source_file": "seed/core/daemon.py", "source_location": "L279", "weight": 1.0}, {"source": "core_daemon_backgrounddaemon_enqueue", "target": "core_daemon_proactivitycandidate", "relation": "references", "context": "parameter_type", "confidence": "EXTRACTED", "source_file": "seed/core/daemon.py", "source_location": "L279", "weight": 1.0}, {"source": "core_daemon_backgrounddaemon", "target": "core_daemon_backgrounddaemon_suppress_category", "relation": "method", "confidence": "EXTRACTED", "source_file": "seed/core/daemon.py", "source_location": "L296", "weight": 1.0}, {"source": "core_daemon_backgrounddaemon", "target": "core_daemon_backgrounddaemon_review", "relation": "method", "confidence": "EXTRACTED", "source_file": "seed/core/daemon.py", "source_location": "L305", "weight": 1.0}, {"source": "core_daemon_backgrounddaemon", "target": "core_daemon_backgrounddaemon_loop", "relation": "method", "confidence": "EXTRACTED", "source_file": "seed/core/daemon.py", "source_location": "L331", "weight": 1.0}, {"source": "core_daemon_backgrounddaemon", "target": "core_daemon_backgrounddaemon_tick", "relation": "method", "confidence": "EXTRACTED", "source_file": "seed/core/daemon.py", "source_location": "L337", "weight": 1.0}, {"source": "core_daemon_backgrounddaemon", "target": "core_daemon_backgrounddaemon_tick_locked", "relation": "method", "confidence": "EXTRACTED", "source_file": "seed/core/daemon.py", "source_location": "L344", "weight": 1.0}, {"source": "core_daemon_backgrounddaemon", "target": "core_daemon_backgrounddaemon_apply_decision", "relation": "method", "confidence": "EXTRACTED", "source_file": "seed/core/daemon.py", "source_location": "L378", "weight": 1.0}, {"source": "core_daemon_backgrounddaemon_apply_decision", "target": "core_daemon_proactivitydecision", "relation": "references", "context": "parameter_type", "confidence": "EXTRACTED", "source_file": "seed/core/daemon.py", "source_location": "L378", "weight": 1.0}, {"source": "core_daemon_backgrounddaemon", "target": "core_daemon_backgrounddaemon_row_to_candidate", "relation": "method", "confidence": "EXTRACTED", "source_file": "seed/core/daemon.py", "source_location": "L395", "weight": 1.0}, {"source": "core_daemon_backgrounddaemon_row_to_candidate", "target": "core_daemon_proactivitycandidate", "relation": "references", "context": "return_type", "confidence": "EXTRACTED", "source_file": "seed/core/daemon.py", "source_location": "L395", "weight": 1.0}, {"source": "c_users_cristian_documents_progetti_jarvis_frameworkutenti_seed_seed_core_daemon_py", "target": "core_daemon_new_candidate_id", "relation": "contains", "confidence": "EXTRACTED", "source_file": "seed/core/daemon.py", "source_location": "L409", "weight": 1.0}, {"source": "core_daemon_clamp_cost", "target": "core_daemon_daemonerror", "relation": "calls", "context": "call", "confidence": "EXTRACTED", "source_file": "seed/core/daemon.py", "source_location": "L78", "weight": 1.0}, {"source": "core_daemon_proactivitycandidate_validate", "target": "core_daemon_daemonerror", "relation": "calls", "context": "call", "confidence": "EXTRACTED", "source_file": "seed/core/daemon.py", "source_location": "L99", "weight": 1.0}, {"source": "core_daemon_proactivitycandidate_validate", "target": "core_daemon_clamp_cost", "relation": "calls", "context": "call", "confidence": "EXTRACTED", "source_file": "seed/core/daemon.py", "source_location": "L103", "weight": 1.0}, {"source": "core_daemon_decide_proactivity", "target": "core_daemon_proactivitycandidate_validate", "relation": "calls", "context": "call", "confidence": "EXTRACTED", "source_file": "seed/core/daemon.py", "source_location": "L146", "weight": 1.0}, {"source": "core_daemon_decide_proactivity", "target": "core_daemon_governed_net_value", "relation": "calls", "context": "call", "confidence": "EXTRACTED", "source_file": "seed/core/daemon.py", "source_location": "L147", "weight": 1.0}, {"source": "core_daemon_decide_proactivity", "target": "core_daemon_proactivitydecision", "relation": "calls", "context": "call", "confidence": "EXTRACTED", "source_file": "seed/core/daemon.py", "source_location": "L151", "weight": 1.0}, {"source": "core_daemon_backgrounddaemon_enqueue", "target": "core_daemon_proactivitycandidate_validate", "relation": "calls", "context": "call", "confidence": "EXTRACTED", "source_file": "seed/core/daemon.py", "source_location": "L282", "weight": 1.0}, {"source": "core_daemon_backgrounddaemon_enqueue", "target": "core_daemon_governed_net_value", "relation": "calls", "context": "call", "confidence": "EXTRACTED", "source_file": "seed/core/daemon.py", "source_location": "L287", "weight": 1.0}, {"source": "core_daemon_backgrounddaemon_suppress_category", "target": "core_daemon_daemonerror", "relation": "calls", "context": "call", "confidence": "EXTRACTED", "source_file": "seed/core/daemon.py", "source_location": "L298", "weight": 1.0}, {"source": "core_daemon_backgrounddaemon_loop", "target": "core_daemon_backgrounddaemon_tick", "relation": "calls", "context": "call", "confidence": "EXTRACTED", "source_file": "seed/core/daemon.py", "source_location": "L333", "weight": 1.0}, {"source": "core_daemon_backgrounddaemon_tick", "target": "core_daemon_backgrounddaemon_tick_locked", "relation": "calls", "context": "call", "confidence": "EXTRACTED", "source_file": "seed/core/daemon.py", "source_location": "L340", "weight": 1.0}, {"source": "core_daemon_backgrounddaemon_tick_locked", "target": "core_daemon_heartbeatstats", "relation": "calls", "context": "call", "confidence": "EXTRACTED", "source_file": "seed/core/daemon.py", "source_location": "L349", "weight": 1.0}, {"source": "core_daemon_backgrounddaemon_tick_locked", "target": "core_daemon_decide_proactivity", "relation": "calls", "context": "call", "confidence": "EXTRACTED", "source_file": "seed/core/daemon.py", "source_location": "L355", "weight": 1.0}, {"source": "core_daemon_backgrounddaemon_tick_locked", "target": "core_daemon_backgrounddaemon_row_to_candidate", "relation": "calls", "context": "call", "confidence": "EXTRACTED", "source_file": "seed/core/daemon.py", "source_location": "L356", "weight": 1.0}, {"source": "core_daemon_backgrounddaemon_tick_locked", "target": "core_daemon_heartbeatstats_record", "relation": "calls", "context": "call", "confidence": "EXTRACTED", "source_file": "seed/core/daemon.py", "source_location": "L363", "weight": 1.0}, {"source": "core_daemon_backgrounddaemon_tick_locked", "target": "core_daemon_backgrounddaemon_apply_decision", "relation": "calls", "context": "call", "confidence": "EXTRACTED", "source_file": "seed/core/daemon.py", "source_location": "L364", "weight": 1.0}, {"source": "core_daemon_backgrounddaemon_tick_locked", "target": "core_daemon_build_heartbeat", "relation": "calls", "context": "call", "confidence": "EXTRACTED", "source_file": "seed/core/daemon.py", "source_location": "L368", "weight": 1.0}, {"source": "core_daemon_backgrounddaemon_row_to_candidate", "target": "core_daemon_proactivitycandidate", "relation": "calls", "context": "call", "confidence": "EXTRACTED", "source_file": "seed/core/daemon.py", "source_location": "L396", "weight": 1.0}, {"source": "core_daemon_rationale_1", "target": "c_users_cristian_documents_progetti_jarvis_frameworkutenti_seed_seed_core_daemon_py", "relation": "rationale_for", "confidence": "EXTRACTED", "source_file": "seed/core/daemon.py", "source_location": "L1", "weight": 1.0}, {"source": "core_daemon_rationale_72", "target": "core_daemon_daemonerror", "relation": "rationale_for", "confidence": "EXTRACTED", "source_file": "seed/core/daemon.py", "source_location": "L72", "weight": 1.0}, {"source": "core_daemon_rationale_84", "target": "core_daemon_proactivitycandidate", "relation": "rationale_for", "confidence": "EXTRACTED", "source_file": "seed/core/daemon.py", "source_location": "L84", "weight": 1.0}, {"source": "core_daemon_rationale_119", "target": "core_daemon_governed_net_value", "relation": "rationale_for", "confidence": "EXTRACTED", "source_file": "seed/core/daemon.py", "source_location": "L119", "weight": 1.0}, {"source": "core_daemon_rationale_138", "target": "core_daemon_decide_proactivity", "relation": "rationale_for", "confidence": "EXTRACTED", "source_file": "seed/core/daemon.py", "source_location": "L138", "weight": 1.0}, {"source": "core_daemon_rationale_193", "target": "core_daemon_build_heartbeat", "relation": "rationale_for", "confidence": "EXTRACTED", "source_file": "seed/core/daemon.py", "source_location": "L193", "weight": 1.0}, {"source": "core_daemon_rationale_220", "target": "core_daemon_backgrounddaemon", "relation": "rationale_for", "confidence": "EXTRACTED", "source_file": "seed/core/daemon.py", "source_location": "L220", "weight": 1.0}, {"source": "core_daemon_rationale_280", "target": "core_daemon_backgrounddaemon_enqueue", "relation": "rationale_for", "confidence": "EXTRACTED", "source_file": "seed/core/daemon.py", "source_location": "L280", "weight": 1.0}, {"source": "core_daemon_rationale_306", "target": "core_daemon_backgrounddaemon_review", "relation": "rationale_for", "confidence": "EXTRACTED", "source_file": "seed/core/daemon.py", "source_location": "L306", "weight": 1.0}], "raw_calls": [{"caller_nid": "core_daemon_proactivitycandidate_validate", "callee": "fullmatch", "is_member_call": true, "source_file": "C:\\Users\\Cristian\\Documents\\Progetti\\JARVIS\\FrameworkUtenti\\seed\\seed\\core\\daemon.py", "source_location": "L100"}, {"caller_nid": "core_daemon_heartbeatstats_record", "callee": "get", "is_member_call": true, "source_file": "C:\\Users\\Cristian\\Documents\\Progetti\\JARVIS\\FrameworkUtenti\\seed\\seed\\core\\daemon.py", "source_location": "L186"}, {"caller_nid": "core_daemon_backgrounddaemon_init", "callee": "Event", "is_member_call": true, "source_file": "C:\\Users\\Cristian\\Documents\\Progetti\\JARVIS\\FrameworkUtenti\\seed\\seed\\core\\daemon.py", "source_location": "L247"}, {"caller_nid": "core_daemon_backgrounddaemon_init", "callee": "Lock", "is_member_call": true, "source_file": "C:\\Users\\Cristian\\Documents\\Progetti\\JARVIS\\FrameworkUtenti\\seed\\seed\\core\\daemon.py", "source_location": "L248"}, {"caller_nid": "core_daemon_backgrounddaemon_start", "callee": "_audit", "is_member_call": true, "source_file": "C:\\Users\\Cristian\\Documents\\Progetti\\JARVIS\\FrameworkUtenti\\seed\\seed\\core\\daemon.py", "source_location": "L254"}, {"caller_nid": "core_daemon_backgrounddaemon_start", "callee": "info", "is_member_call": true, "source_file": "C:\\Users\\Cristian\\Documents\\Progetti\\JARVIS\\FrameworkUtenti\\seed\\seed\\core\\daemon.py", "source_location": "L255"}, {"caller_nid": "core_daemon_backgrounddaemon_start", "callee": "is_alive", "is_member_call": true, "source_file": "C:\\Users\\Cristian\\Documents\\Progetti\\JARVIS\\FrameworkUtenti\\seed\\seed\\core\\daemon.py", "source_location": "L257"}, {"caller_nid": "core_daemon_backgrounddaemon_start", "callee": "clear", "is_member_call": true, "source_file": "C:\\Users\\Cristian\\Documents\\Progetti\\JARVIS\\FrameworkUtenti\\seed\\seed\\core\\daemon.py", "source_location": "L259"}, {"caller_nid": "core_daemon_backgrounddaemon_start", "callee": "Thread", "is_member_call": true, "source_file": "C:\\Users\\Cristian\\Documents\\Progetti\\JARVIS\\FrameworkUtenti\\seed\\seed\\core\\daemon.py", "source_location": "L260"}, {"caller_nid": "core_daemon_backgrounddaemon_start", "callee": "_audit", "is_member_call": true, "source_file": "C:\\Users\\Cristian\\Documents\\Progetti\\JARVIS\\FrameworkUtenti\\seed\\seed\\core\\daemon.py", "source_location": "L263"}, {"caller_nid": "core_daemon_backgrounddaemon_start", "callee": "info", "is_member_call": true, "source_file": "C:\\Users\\Cristian\\Documents\\Progetti\\JARVIS\\FrameworkUtenti\\seed\\seed\\core\\daemon.py", "source_location": "L265"}, {"caller_nid": "core_daemon_backgrounddaemon_stop", "callee": "join", "is_member_call": true, "source_file": "C:\\Users\\Cristian\\Documents\\Progetti\\JARVIS\\FrameworkUtenti\\seed\\seed\\core\\daemon.py", "source_location": "L271"}, {"caller_nid": "core_daemon_backgrounddaemon_stop", "callee": "_audit", "is_member_call": true, "source_file": "C:\\Users\\Cristian\\Documents\\Progetti\\JARVIS\\FrameworkUtenti\\seed\\seed\\core\\daemon.py", "source_location": "L272"}, {"caller_nid": "core_daemon_backgrounddaemon_running", "callee": "is_alive", "is_member_call": true, "source_file": "C:\\Users\\Cristian\\Documents\\Progetti\\JARVIS\\FrameworkUtenti\\seed\\seed\\core\\daemon.py", "source_location": "L276"}, {"caller_nid": "core_daemon_backgrounddaemon_enqueue", "callee": "enqueue_proactivity", "is_member_call": true, "source_file": "C:\\Users\\Cristian\\Documents\\Progetti\\JARVIS\\FrameworkUtenti\\seed\\seed\\core\\daemon.py", "source_location": "L283"}, {"caller_nid": "core_daemon_backgrounddaemon_suppress_category", "callee": "add", "is_member_call": true, "source_file": "C:\\Users\\Cristian\\Documents\\Progetti\\JARVIS\\FrameworkUtenti\\seed\\seed\\core\\daemon.py", "source_location": "L300"}, {"caller_nid": "core_daemon_backgrounddaemon_suppress_category", "callee": "discard", "is_member_call": true, "source_file": "C:\\Users\\Cristian\\Documents\\Progetti\\JARVIS\\FrameworkUtenti\\seed\\seed\\core\\daemon.py", "source_location": "L302"}, {"caller_nid": "core_daemon_backgrounddaemon_review", "callee": "daemon_state", "is_member_call": true, "source_file": "C:\\Users\\Cristian\\Documents\\Progetti\\JARVIS\\FrameworkUtenti\\seed\\seed\\core\\daemon.py", "source_location": "L308"}, {"caller_nid": "core_daemon_backgrounddaemon_review", "callee": "get", "is_member_call": true, "source_file": "C:\\Users\\Cristian\\Documents\\Progetti\\JARVIS\\FrameworkUtenti\\seed\\seed\\core\\daemon.py", "source_location": "L324"}, {"caller_nid": "core_daemon_backgrounddaemon_review", "callee": "get", "is_member_call": true, "source_file": "C:\\Users\\Cristian\\Documents\\Progetti\\JARVIS\\FrameworkUtenti\\seed\\seed\\core\\daemon.py", "source_location": "L325"}, {"caller_nid": "core_daemon_backgrounddaemon_review", "callee": "get", "is_member_call": true, "source_file": "C:\\Users\\Cristian\\Documents\\Progetti\\JARVIS\\FrameworkUtenti\\seed\\seed\\core\\daemon.py", "source_location": "L326"}, {"caller_nid": "core_daemon_backgrounddaemon_review", "callee": "proactivity_status_counts", "is_member_call": true, "source_file": "C:\\Users\\Cristian\\Documents\\Progetti\\JARVIS\\FrameworkUtenti\\seed\\seed\\core\\daemon.py", "source_location": "L327"}, {"caller_nid": "core_daemon_backgrounddaemon_loop", "callee": "wait", "is_member_call": true, "source_file": "C:\\Users\\Cristian\\Documents\\Progetti\\JARVIS\\FrameworkUtenti\\seed\\seed\\core\\daemon.py", "source_location": "L334"}, {"caller_nid": "core_daemon_backgrounddaemon_tick", "callee": "exception", "is_member_call": true, "source_file": "C:\\Users\\Cristian\\Documents\\Progetti\\JARVIS\\FrameworkUtenti\\seed\\seed\\core\\daemon.py", "source_location": "L342"}, {"caller_nid": "core_daemon_backgrounddaemon_tick_locked", "callee": "_clock", "is_member_call": true, "source_file": "C:\\Users\\Cristian\\Documents\\Progetti\\JARVIS\\FrameworkUtenti\\seed\\seed\\core\\daemon.py", "source_location": "L345"}, {"caller_nid": "core_daemon_backgrounddaemon_tick_locked", "callee": "daemon_state", "is_member_call": true, "source_file": "C:\\Users\\Cristian\\Documents\\Progetti\\JARVIS\\FrameworkUtenti\\seed\\seed\\core\\daemon.py", "source_location": "L346"}, {"caller_nid": "core_daemon_backgrounddaemon_tick_locked", "callee": "get", "is_member_call": true, "source_file": "C:\\Users\\Cristian\\Documents\\Progetti\\JARVIS\\FrameworkUtenti\\seed\\seed\\core\\daemon.py", "source_location": "L347"}, {"caller_nid": "core_daemon_backgrounddaemon_tick_locked", "callee": "_can_run", "is_member_call": true, "source_file": "C:\\Users\\Cristian\\Documents\\Progetti\\JARVIS\\FrameworkUtenti\\seed\\seed\\core\\daemon.py", "source_location": "L348"}, {"caller_nid": "core_daemon_backgrounddaemon_tick_locked", "callee": "proactivity_queue_items", "is_member_call": true, "source_file": "C:\\Users\\Cristian\\Documents\\Progetti\\JARVIS\\FrameworkUtenti\\seed\\seed\\core\\daemon.py", "source_location": "L350"}, {"caller_nid": "core_daemon_backgrounddaemon_tick_locked", "callee": "get", "is_member_call": true, "source_file": "C:\\Users\\Cristian\\Documents\\Progetti\\JARVIS\\FrameworkUtenti\\seed\\seed\\core\\daemon.py", "source_location": "L353"}, {"caller_nid": "core_daemon_backgrounddaemon_tick_locked", "callee": "proactivity_queue_items", "is_member_call": true, "source_file": "C:\\Users\\Cristian\\Documents\\Progetti\\JARVIS\\FrameworkUtenti\\seed\\seed\\core\\daemon.py", "source_location": "L354"}, {"caller_nid": "core_daemon_backgrounddaemon_tick_locked", "callee": "update_daemon_state", "is_member_call": true, "source_file": "C:\\Users\\Cristian\\Documents\\Progetti\\JARVIS\\FrameworkUtenti\\seed\\seed\\core\\daemon.py", "source_location": "L370"}, {"caller_nid": "core_daemon_backgrounddaemon_tick_locked", "callee": "get", "is_member_call": true, "source_file": "C:\\Users\\Cristian\\Documents\\Progetti\\JARVIS\\FrameworkUtenti\\seed\\seed\\core\\daemon.py", "source_location": "L373"}, {"caller_nid": "core_daemon_backgrounddaemon_tick_locked", "callee": "_audit", "is_member_call": true, "source_file": "C:\\Users\\Cristian\\Documents\\Progetti\\JARVIS\\FrameworkUtenti\\seed\\seed\\core\\daemon.py", "source_location": "L376"}, {"caller_nid": "core_daemon_backgrounddaemon_apply_decision", "callee": "set_proactivity_status", "is_member_call": true, "source_file": "C:\\Users\\Cristian\\Documents\\Progetti\\JARVIS\\FrameworkUtenti\\seed\\seed\\core\\daemon.py", "source_location": "L387"}, {"caller_nid": "core_daemon_new_candidate_id", "callee": "uuid4", "is_member_call": true, "source_file": "C:\\Users\\Cristian\\Documents\\Progetti\\JARVIS\\FrameworkUtenti\\seed\\seed\\core\\daemon.py", "source_location": "L410"}]}